MANIFEST.in
README.md
setup.py
bin/gen_names_mkopys.bat
gen_names_mkopys/__init__.py
gen_names_mkopys/gen_names_mkopys.py
gen_names_mkopys.egg-info/PKG-INFO
gen_names_mkopys.egg-info/SOURCES.txt
gen_names_mkopys.egg-info/dependency_links.txt
gen_names_mkopys.egg-info/requires.txt
gen_names_mkopys.egg-info/top_level.txt