Metadata-Version: 1.0
Name: gen-names-mkopys
Version: 1.0.0
Summary: Generate random names with lenght mkopys
Home-page: https://github.com/treyhunner/names
Author: Michal Kopys
Author-email: mikopys@gmail.com
License: UNKNOWN
Keywords: random names
Platform: UNKNOWN
